clear_watermark/__init__.py
clear_watermark-1.0.1.dist-info/LICENSE.txt
clear_watermark-1.0.1.dist-info/METADATA
clear_watermark-1.0.1.dist-info/WHEEL
clear_watermark-1.0.1.dist-info/top_level.txt
clear_watermark-1.0.1.dist-info/RECORD
