Metadata-Version: 2.1
Name: clear-watermark
Version: 1.0.1
Summary: It uses OOP to insert one image as a watermark on other image.
Home-page: https://github.com/carlosmperilla/clear-watermark
Author: carlosmperilla
Author-email: carlosperillaprogramacion@gmail.com
License: MIT
Keywords: watermark image branding mark editions edition package carlosmperilla
Classifier: Programming Language :: Python :: 3
Classifier: License :: OSI Approved :: MIT License
Classifier: Operating System :: OS Independent
License-File: LICENSE.txt
Requires-Dist: Pillow (>=7.2.0)
